[{"Id":5716,"Title":"","Value":"No.5695谢谢你R5Rﾟ ∀ﾟ)ノ祝福收到嘞 确实睡得不错","FollowId":5383,"PlateId":5,"Status":0,"ReplyArr":"[]","UserId":957,"Time":1665503161,"MediaUrl":"[]","ReplyCount":0,"TopStatus":0,"LastReplyTime":1665503161,"SageAddId":"[]","SageSubId":"[]","Name":"pmLIR19"},{"Id":5717,"Title":"","Value":"是时候复习学科知识了 唰啦唰啦地过真爽 感谢曾经好好背书的我","FollowId":5383,"PlateId":5,"Status":0,"ReplyArr":"[]","UserId":957,"Time":1665503251,"MediaUrl":"[]","ReplyCount":0,"TopStatus":0,"LastReplyTime":1665503251,"SageAddId":"[]","SageSubId":"[]","Name":"pmLIR19"}]