[{"Id":4409,"Title":"","Value":"我操真是低到吐血\n即将开始投简历……","FollowId":3950,"PlateId":5,"Status":0,"ReplyArr":"[]","UserId":174,"Time":1659090952,"MediaUrl":"[]","ReplyCount":0,"TopStatus":0,"LastReplyTime":1659090952,"SageAddId":"[]","SageSubId":"[]","Name":"k4zb5Iu"},{"Id":4410,"Title":"","Value":"直面鲜血淋漓又惨淡的现实","FollowId":3950,"PlateId":5,"Status":0,"ReplyArr":"[]","UserId":174,"Time":1659092094,"MediaUrl":"[]","ReplyCount":0,"TopStatus":0,"LastReplyTime":1659092094,"SageAddId":"[]","SageSubId":"[]","Name":"k4zb5Iu"}]