[{"Id":4704,"Title":"","Value":"No.4703其实可以搞(;´ヮ`)7","FollowId":3950,"PlateId":5,"Status":0,"ReplyArr":"[]","UserId":10,"Time":1660470968,"MediaUrl":"[]","ReplyCount":0,"TopStatus":0,"LastReplyTime":1660470968,"SageAddId":"[]","SageSubId":"[]","Name":"R5RCGeZ"},{"Id":4705,"Title":"","Value":"No.4680(=ﾟωﾟ)=","FollowId":4539,"PlateId":5,"Status":0,"ReplyArr":"[]","UserId":10,"Time":1660471017,"MediaUrl":"[]","ReplyCount":0,"TopStatus":0,"LastReplyTime":1660471017,"SageAddId":"[]","SageSubId":"[]","Name":"R5RCGeZ"}]