[{"Id":3535,"Title":"","Value":"No.3533是宫斗剧中的那种指甲吗","FollowId":457,"PlateId":5,"Status":0,"ReplyArr":"[]","UserId":412,"Time":1655712146,"MediaUrl":"[]","ReplyCount":0,"TopStatus":0,"LastReplyTime":1655712146,"SageAddId":"[]","SageSubId":"[]","Name":"ri5spPC"},{"Id":3536,"Title":"","Value":"nullNo.3535\n那种护甲穿出门别人指不定以为我( ﾟ∀。)\n大概类似如图长度，是可以拆卸的","FollowId":457,"PlateId":5,"Status":0,"ReplyArr":"[]","UserId":174,"Time":1655713707,"MediaUrl":"[{\"id\":\"5772E32D-F33C-4086-AFBB-650B9D3F11AD\",\"url\":\"https://s2.loli.net/2022/06/20/Bw1o9LbsGenQNgf.jpg\",\"thumbnailUrl\":\"https://s2.loli.net/2022/06/20/Bw1o9LbsGenQNgf.jpg\"}]","ReplyCount":0,"TopStatus":0,"LastReplyTime":1655713707,"SageAddId":"[]","SageSubId":"[]","Name":"k4zb5Iu"},{"Id":3537,"Title":"","Value":"静观其变吧","FollowId":3508,"PlateId":1,"Status":0,"ReplyArr":"[]","UserId":785,"Time":1655714668,"MediaUrl":"[]","ReplyCount":0,"TopStatus":0,"LastReplyTime":1655714668,"SageAddId":"[]","SageSubId":"[]","Name":"lRH4DS5"}]