[{"Id":6667,"Title":"","Value":"No.6661今天也居家办公了一天(｀･ω･)","FollowId":5450,"PlateId":5,"Status":0,"ReplyArr":"[]","UserId":10,"Time":1671530852,"MediaUrl":"[]","ReplyCount":0,"TopStatus":0,"LastReplyTime":1671530852,"SageAddId":"[]","SageSubId":"[]","Name":"R5RCGeZ"},{"Id":6668,"Title":"","Value":"No.6666好靓的串号","FollowId":5450,"PlateId":5,"Status":0,"ReplyArr":"[]","UserId":10,"Time":1671530885,"MediaUrl":"[]","ReplyCount":0,"TopStatus":0,"LastReplyTime":1671530885,"SageAddId":"[]","SageSubId":"[]","Name":"R5RCGeZ"},{"Id":6669,"Title":"","Value":"No.6667如果不考虑通勤，我还是愿意回去上的","FollowId":5450,"PlateId":5,"Status":0,"ReplyArr":"[]","UserId":174,"Time":1671533397,"MediaUrl":"[]","ReplyCount":0,"TopStatus":0,"LastReplyTime":1671533397,"SageAddId":"[]","SageSubId":"[]","Name":"k4zb5Iu"},{"Id":6670,"Title":"","Value":"昨天路过一家药店，要啥没啥，我的药还是在拼多多买菜买的( ﾟ∀。)","FollowId":5450,"PlateId":5,"Status":0,"ReplyArr":"[]","UserId":174,"Time":1671533553,"MediaUrl":"[]","ReplyCount":0,"TopStatus":0,"LastReplyTime":1671533553,"SageAddId":"[]","SageSubId":"[]","Name":"k4zb5Iu"}]