[{"Id":3427,"Title":"","Value":"No.3420\n如果以你的理解来执行，那这也太难了\n1.有时候由于人的独特性格和行文/画风，隐约还是可以推断出来的。\n2.会有喜欢扮演的人故意留下特征，供别人寻摸\n3.追星族饼干，小圈子型饼干，认亲型饼干\n\n参考一下晋江粉论坛？具体去到某个串内发言，在此串就是相同饼干，但是离开再到别的串那就是不同饼干\n甚至全匿名到只区分po主？\n\n关于你说的没有管理，我觉得不太行，主要还是现在咱们人少，要是人一多……\n\n","FollowId":457,"PlateId":5,"Status":0,"ReplyArr":"[]","UserId":174,"Time":1655401037,"MediaUrl":"[]","ReplyCount":0,"TopStatus":0,"LastReplyTime":1655401037,"SageAddId":"[]","SageSubId":"[]","Name":"k4zb5Iu"},{"Id":3428,"Title":"","Value":"No.3421\n至少比以前好･ﾟ( ﾉヮ´ )\n刚看了一下，还好，只能说等时间验证吧","FollowId":457,"PlateId":5,"Status":0,"ReplyArr":"[]","UserId":174,"Time":1655401564,"MediaUrl":"[]","ReplyCount":0,"TopStatus":0,"LastReplyTime":1655401564,"SageAddId":"[]","SageSubId":"[]","Name":"k4zb5Iu"},{"Id":3429,"Title":"","Value":"能不能添加一个草稿功能捏，一不小心刷新一下整段话就无了(;´Д`)","FollowId":0,"PlateId":2,"Status":0,"ReplyArr":"[]","UserId":174,"Time":1655401630,"MediaUrl":"[]","ReplyCount":1,"TopStatus":0,"LastReplyTime":1655427034,"SageAddId":"[]","SageSubId":"[]","Name":"k4zb5Iu"}]