[{"Id":5848,"Title":"","Value":"摸摸","FollowId":5846,"PlateId":1,"Status":0,"ReplyArr":"[]","UserId":174,"Time":1666329041,"MediaUrl":"[]","ReplyCount":0,"TopStatus":0,"LastReplyTime":1666329041,"SageAddId":"[]","SageSubId":"[]","Name":"k4zb5Iu"},{"Id":5849,"Title":"","Value":"No.5843(=ﾟωﾟ)=准备放假ﾟ ∀ﾟ)ノ","FollowId":4927,"PlateId":5,"Status":0,"ReplyArr":"[]","UserId":10,"Time":1666329638,"MediaUrl":"[]","ReplyCount":0,"TopStatus":0,"LastReplyTime":1666329638,"SageAddId":"[]","SageSubId":"[]","Name":"R5RCGeZ"},{"Id":5850,"Title":"","Value":"No.5844(`ᝫ´ )有啥新乐子吗，最近在看x岛乐子串，还挺有意思","FollowId":5450,"PlateId":5,"Status":0,"ReplyArr":"[]","UserId":10,"Time":1666329697,"MediaUrl":"[]","ReplyCount":0,"TopStatus":0,"LastReplyTime":1666329697,"SageAddId":"[]","SageSubId":"[]","Name":"R5RCGeZ"}]