[{"Id":455,"Title":"","Value":"好耶","FollowId":425,"PlateId":2,"Status":0,"ReplyArr":"[]","UserId":174,"Time":1650320266,"MediaUrl":"[]","ReplyCount":0,"TopStatus":0,"LastReplyTime":1650320266,"SageAddId":"[]","SageSubId":"[]","Name":"k4zb5Iu"},{"Id":456,"Title":"","Value":"No.421|∀` )太棒里","FollowId":416,"PlateId":2,"Status":0,"ReplyArr":"[]","UserId":174,"Time":1650320313,"MediaUrl":"[]","ReplyCount":0,"TopStatus":0,"LastReplyTime":1650320313,"SageAddId":"[]","SageSubId":"[]","Name":"k4zb5Iu"},{"Id":457,"Title":"","Value":"我会是不是望垃圾桶里扔东西","FollowId":0,"PlateId":5,"Status":0,"ReplyArr":"[]","UserId":174,"Time":1650320351,"MediaUrl":"[]","ReplyCount":30,"TopStatus":0,"LastReplyTime":1650631874,"SageAddId":"[]","SageSubId":"[]","Name":"k4zb5Iu"},{"Id":458,"Title":"","Value":"哦fuck串首就错字","FollowId":457,"PlateId":5,"Status":0,"ReplyArr":"[]","UserId":174,"Time":1650320370,"MediaUrl":"[]","ReplyCount":0,"TopStatus":0,"LastReplyTime":1650320370,"SageAddId":"[]","SageSubId":"[]","Name":"k4zb5Iu"},{"Id":459,"Title":"","Value":"而且脸错三个","FollowId":457,"PlateId":5,"Status":0,"ReplyArr":"[]","UserId":174,"Time":1650320389,"MediaUrl":"[]","ReplyCount":0,"TopStatus":0,"LastReplyTime":1650320389,"SageAddId":"[]","SageSubId":"[]","Name":"k4zb5Iu"},{"Id":460,"Title":"","Value":"我还会是不是看看垃圾桶里有没有多东西","FollowId":457,"PlateId":5,"Status":0,"ReplyArr":"[]","UserId":174,"Time":1650320494,"MediaUrl":"[]","ReplyCount":0,"TopStatus":0,"LastReplyTime":1650320494,"SageAddId":"[]","SageSubId":"[]","Name":"k4zb5Iu"},{"Id":461,"Title":"","Value":"OMG！\n我的垃圾桶上时间线了((((ﾟДﾟ≡ﾟДﾟ))))","FollowId":457,"PlateId":5,"Status":0,"ReplyArr":"[]","UserId":174,"Time":1650320572,"MediaUrl":"[]","ReplyCount":0,"TopStatus":0,"LastReplyTime":1650320572,"SageAddId":"[]","SageSubId":"[]","Name":"k4zb5Iu"},{"Id":462,"Title":"","Value":"炸","FollowId":70,"PlateId":3,"Status":0,"ReplyArr":"[]","UserId":174,"Time":1650320626,"MediaUrl":"[]","ReplyCount":0,"TopStatus":0,"LastReplyTime":1650320626,"SageAddId":"[]","SageSubId":"[]","Name":"k4zb5Iu"}]