[{"Id":3074,"Title":"","Value":"No.3064嘿，我就知道有人会提出这个问题ﾟ∀ﾟ)σ\n这里的概率可是和普通填三个的概率不一样的哦，普通填三个的概率是均等的三分之一，而示例中的概率在嵌套中的两个选项分别是四分之一而嵌套外的是二分之一哦ﾟ∀ﾟ)σ","FollowId":3062,"PlateId":2,"Status":0,"ReplyArr":"[]","UserId":10,"Time":1654734613,"MediaUrl":"[]","ReplyCount":0,"TopStatus":0,"LastReplyTime":1654734613,"SageAddId":"[]","SageSubId":"[]","Name":"R5RCGeZ"},{"Id":3075,"Title":"","Value":"No.3064还有许多新特性，连我都没发现的呢| ω・´)","FollowId":3062,"PlateId":2,"Status":0,"ReplyArr":"[]","UserId":10,"Time":1654734691,"MediaUrl":"[]","ReplyCount":0,"TopStatus":0,"LastReplyTime":1654734691,"SageAddId":"[]","SageSubId":"[]","Name":"R5RCGeZ"},{"Id":3076,"Title":"","Value":"No.3064比如说这个[`ᝫ´ ] = `ᝫ´ ","FollowId":3062,"PlateId":2,"Status":0,"ReplyArr":"[]","UserId":10,"Time":1654734739,"MediaUrl":"[]","ReplyCount":0,"TopStatus":0,"LastReplyTime":1654734739,"SageAddId":"[]","SageSubId":"[]","Name":"R5RCGeZ"},{"Id":3077,"Title":"","Value":"No.3064因为bog表情中的表情被解析为原子了(`ᝫ´ )","FollowId":3062,"PlateId":2,"Status":0,"ReplyArr":"[]","UserId":10,"Time":1654734784,"MediaUrl":"[]","ReplyCount":0,"TopStatus":0,"LastReplyTime":1654734784,"SageAddId":"[]","SageSubId":"[]","Name":"R5RCGeZ"}]