[{"Id":1654,"Title":"","Value":"No.1649 为什么这两只鸽子这么大\n","FollowId":885,"PlateId":1,"Status":0,"ReplyArr":"[]","UserId":510,"Time":1652519983,"MediaUrl":"[]","ReplyCount":0,"TopStatus":0,"LastReplyTime":1652519983,"SageAddId":"[]","SageSubId":"[]","Name":"K5Z80Mp"},{"Id":1655,"Title":"","Value":"No.1652查重率50%(`ᝫ´ )","FollowId":457,"PlateId":5,"Status":0,"ReplyArr":"[]","UserId":10,"Time":1652520040,"MediaUrl":"[]","ReplyCount":0,"TopStatus":0,"LastReplyTime":1652520040,"SageAddId":"[]","SageSubId":"[]","Name":"R5RCGeZ"},{"Id":1656,"Title":"","Value":"No.1655\n( ᑭ`д´)ᓀ→→→→→→→→))д´)ᑫ","FollowId":457,"PlateId":5,"Status":0,"ReplyArr":"[]","UserId":174,"Time":1652520212,"MediaUrl":"[]","ReplyCount":0,"TopStatus":0,"LastReplyTime":1652520212,"SageAddId":"[]","SageSubId":"[]","Name":"k4zb5Iu"},{"Id":1657,"Title":"","Value":"可恶啊，为什么我的同事不是已经结婚就是准备结婚，呃啊呃啊呃啊","FollowId":457,"PlateId":5,"Status":0,"ReplyArr":"[]","UserId":174,"Time":1652520293,"MediaUrl":"[]","ReplyCount":0,"TopStatus":0,"LastReplyTime":1652520293,"SageAddId":"[]","SageSubId":"[]","Name":"k4zb5Iu"}]