[{"Id":6557,"Title":"","Value":"No.6550(´ﾟДﾟ`)(　д ) ﾟ ﾟ\ngkd给我做个贴钻的棋盘格(`ε´ )","FollowId":5450,"PlateId":5,"Status":0,"ReplyArr":"[]","UserId":174,"Time":1670818028,"MediaUrl":"[]","ReplyCount":0,"TopStatus":0,"LastReplyTime":1670818028,"SageAddId":"[]","SageSubId":"[]","Name":"k4zb5Iu"},{"Id":6558,"Title":"","Value":"No.6551垃圾，下次不去了","FollowId":5450,"PlateId":5,"Status":0,"ReplyArr":"[]","UserId":174,"Time":1670818045,"MediaUrl":"[]","ReplyCount":0,"TopStatus":0,"LastReplyTime":1670818045,"SageAddId":"[]","SageSubId":"[]","Name":"k4zb5Iu"},{"Id":6559,"Title":"","Value":"No.6554No.6555\n囤了一百年终于可以拉出来用了(`ヮ´ )","FollowId":5450,"PlateId":5,"Status":0,"ReplyArr":"[]","UserId":174,"Time":1670818095,"MediaUrl":"[{\"id\":\"646c922abdb0157ddd556c2db1ae2f5e.JPG\",\"url\":\"https://islander-image.juhuan.store/646c922abdb0157ddd556c2db1ae2f5e.JPG\",\"thumbnailUrl\":\"https://islander-image.juhuan.store/646c922abdb0157ddd556c2db1ae2f5e.JPG\"}]","ReplyCount":0,"TopStatus":0,"LastReplyTime":1670818095,"SageAddId":"[]","SageSubId":"[]","Name":"k4zb5Iu"},{"Id":6560,"Title":"","Value":"No.6556(|||ﾟдﾟ）不是放开吗？咋那么会这样？","FollowId":5450,"PlateId":5,"Status":0,"ReplyArr":"[]","UserId":174,"Time":1670818148,"MediaUrl":"[]","ReplyCount":0,"TopStatus":0,"LastReplyTime":1670818148,"SageAddId":"[]","SageSubId":"[]","Name":"k4zb5Iu"},{"Id":6561,"Title":"","Value":"累死我了( ›´ω`‹ )\n鸽摸宁","FollowId":5450,"PlateId":5,"Status":0,"ReplyArr":"[]","UserId":174,"Time":1670818168,"MediaUrl":"[{\"id\":\"3a7e1ca2ac02d0b3a00b7c8fb402f160.jpg\",\"url\":\"https://islander-image.juhuan.store/3a7e1ca2ac02d0b3a00b7c8fb402f160.jpg\",\"thumbnailUrl\":\"https://islander-image.juhuan.store/3a7e1ca2ac02d0b3a00b7c8fb402f160.jpg\"}]","ReplyCount":0,"TopStatus":0,"LastReplyTime":1670818168,"SageAddId":"[]","SageSubId":"[]","Name":"k4zb5Iu"},{"Id":6562,"Title":"","Value":"No.6536不给我看就吃我一拳( ᑭ`д´)ᓀ))д´)ᑫ","FollowId":4927,"PlateId":5,"Status":0,"ReplyArr":"[]","UserId":174,"Time":1670818930,"MediaUrl":"[]","ReplyCount":0,"TopStatus":0,"LastReplyTime":1670818930,"SageAddId":"[]","SageSubId":"[]","Name":"k4zb5Iu"},{"Id":6563,"Title":"","Value":"No.6387(つд⊂)真的吗","FollowId":457,"PlateId":5,"Status":0,"ReplyArr":"[]","UserId":174,"Time":1670818973,"MediaUrl":"[]","ReplyCount":0,"TopStatus":0,"LastReplyTime":1670818973,"SageAddId":"[]","SageSubId":"[]","Name":"k4zb5Iu"},{"Id":6564,"Title":"","Value":"( ﾟ∀。)手还能稳得住吗","FollowId":457,"PlateId":5,"Status":0,"ReplyArr":"[]","UserId":174,"Time":1670819004,"MediaUrl":"[{\"id\":\"7a40db47c66754184e25d5230bc3c41d.jpg\",\"url\":\"https://islander-image.juhuan.store/7a40db47c66754184e25d5230bc3c41d.jpg\",\"thumbnailUrl\":\"https://islander-image.juhuan.store/7a40db47c66754184e25d5230bc3c41d.jpg\"}]","ReplyCount":0,"TopStatus":0,"LastReplyTime":1670819004,"SageAddId":"[]","SageSubId":"[]","Name":"k4zb5Iu"},{"Id":6565,"Title":"","Value":"今天也有怪图放在467","FollowId":5450,"PlateId":5,"Status":0,"ReplyArr":"[]","UserId":174,"Time":1670819033,"MediaUrl":"[]","ReplyCount":0,"TopStatus":0,"LastReplyTime":1670819033,"SageAddId":"[]","SageSubId":"[]","Name":"k4zb5Iu"},{"Id":6566,"Title":"","Value":"No.6553工业( ﾟ∀。)7","FollowId":5572,"PlateId":1,"Status":0,"ReplyArr":"[]","UserId":174,"Time":1670819077,"MediaUrl":"[]","ReplyCount":0,"TopStatus":0,"LastReplyTime":1670819077,"SageAddId":"[]","SageSubId":"[]","Name":"k4zb5Iu"}]