[{"Id":3045,"Title":"","Value":"新a岛有app了，套黎明岛k的壳子\n新发出来的串能够点进去查看，而三个月前的串会显示不存在，但是都挺全的（没有饼干，无法测试是否登录就能看到全部内容）\n( ´_ゝ`)旦","FollowId":2872,"PlateId":4,"Status":0,"ReplyArr":"[]","UserId":690,"Time":1654697361,"MediaUrl":"[{\"id\":\"96CA1CF4-AA4F-4372-ACAF-DBEE1213F22D\",\"url\":\"https://s2.loli.net/2022/06/08/hbygUE3LYRBdz1K.jpg\",\"thumbnailUrl\":\"https://s2.loli.net/2022/06/08/hbygUE3LYRBdz1K.jpg\"},{\"id\":\"3ECAABA3-656E-4923-89F0-646A2F2F0741\",\"url\":\"https://s2.loli.net/2022/06/08/ZJDMtul97CrReIb.jpg\",\"thumbnailUrl\":\"https://s2.loli.net/2022/06/08/ZJDMtul97CrReIb.jpg\"},{\"id\":\"B2CF44AF-C0F0-4536-8479-6B767A871D09\",\"url\":\"https://s2.loli.net/2022/06/08/CFyrVSjOR5viWe3.jpg\",\"thumbnailUrl\":\"https://s2.loli.net/2022/06/08/CFyrVSjOR5viWe3.jpg\"}]","ReplyCount":0,"TopStatus":0,"LastReplyTime":1654697361,"SageAddId":"[]","SageSubId":"[]","Name":"EEj1Evf"},{"Id":3046,"Title":"","Value":"时隔多年终于体会到了吴彦祖有多靓仔","FollowId":457,"PlateId":5,"Status":0,"ReplyArr":"[]","UserId":174,"Time":1654698705,"MediaUrl":"[]","ReplyCount":0,"TopStatus":0,"LastReplyTime":1654698705,"SageAddId":"[]","SageSubId":"[]","Name":"k4zb5Iu"},{"Id":3047,"Title":"","Value":"在找化学老师要她解析的前几年高考题时，感受到了化学老师的热情\n(*ﾟ∀ﾟ*)","FollowId":2945,"PlateId":1,"Status":0,"ReplyArr":"[]","UserId":276,"Time":1654699554,"MediaUrl":"[{\"id\":\"EA4AE505-2106-43D7-84EC-DC60B69EACDF\",\"url\":\"https://s2.loli.net/2022/06/08/KOhC3Zqxy6EWtYL.jpg\",\"thumbnailUrl\":\"https://s2.loli.net/2022/06/08/KOhC3Zqxy6EWtYL.jpg\"}]","ReplyCount":0,"TopStatus":0,"LastReplyTime":1654699554,"SageAddId":"[]","SageSubId":"[]","Name":"DrbUfHl"},{"Id":3048,"Title":"","Value":"确实啊，作为这一届我们学校里唯一一个选考化学的学生和化学老师关门大弟子，化学老师真的对我超级好的(`・ω・´)\n高二的时候她说给上一届高考生蒸了一锅包子吃。今年也蒸了，可小肥没福分，请假了没捞着，只有复读生兄弟们恰到了ﾟ(つд`ﾟ)","FollowId":2945,"PlateId":1,"Status":0,"ReplyArr":"[]","UserId":276,"Time":1654699799,"MediaUrl":"[]","ReplyCount":0,"TopStatus":0,"LastReplyTime":1654699799,"SageAddId":"[]","SageSubId":"[]","Name":"DrbUfHl"},{"Id":3049,"Title":"","Value":"No.2998\nsan值，我的san值ﾟÅﾟ )","FollowId":1186,"PlateId":1,"Status":0,"ReplyArr":"[]","UserId":276,"Time":1654699882,"MediaUrl":"[]","ReplyCount":0,"TopStatus":0,"LastReplyTime":1654699882,"SageAddId":"[]","SageSubId":"[]","Name":"DrbUfHl"},{"Id":3050,"Title":"","Value":"No.3043\nR5R大佬也(｀･ω･)bbbbbbbbb","FollowId":2945,"PlateId":1,"Status":0,"ReplyArr":"[]","UserId":276,"Time":1654699951,"MediaUrl":"[]","ReplyCount":0,"TopStatus":0,"LastReplyTime":1654699951,"SageAddId":"[]","SageSubId":"[]","Name":"DrbUfHl"},{"Id":3051,"Title":"","Value":"No.3031\n肥哥也要吃点好的欧(=ﾟωﾟ)=","FollowId":2945,"PlateId":1,"Status":0,"ReplyArr":"[]","UserId":276,"Time":1654699986,"MediaUrl":"[]","ReplyCount":0,"TopStatus":0,"LastReplyTime":1654699986,"SageAddId":"[]","SageSubId":"[]","Name":"DrbUfHl"}]