[{"Id":5111,"Title":"","Value":"No.5104准备放个新版本上去(=ﾟωﾟ)=","FollowId":3950,"PlateId":5,"Status":0,"ReplyArr":"[]","UserId":10,"Time":1662699870,"MediaUrl":"[]","ReplyCount":0,"TopStatus":0,"LastReplyTime":1662699870,"SageAddId":"[]","SageSubId":"[]","Name":"R5RCGeZ"},{"Id":5112,"Title":"","Value":"最近沉迷异世界舅舅|∀ﾟ","FollowId":3950,"PlateId":5,"Status":0,"ReplyArr":"[]","UserId":10,"Time":1662699886,"MediaUrl":"[]","ReplyCount":0,"TopStatus":0,"LastReplyTime":1662699886,"SageAddId":"[]","SageSubId":"[]","Name":"R5RCGeZ"},{"Id":5113,"Title":"","Value":"No.5100嗨呀，摸鱼升级了下游戏(*´д`)","FollowId":4927,"PlateId":5,"Status":0,"ReplyArr":"[]","UserId":10,"Time":1662699931,"MediaUrl":"[]","ReplyCount":0,"TopStatus":0,"LastReplyTime":1662699931,"SageAddId":"[]","SageSubId":"[]","Name":"R5RCGeZ"},{"Id":5114,"Title":"","Value":"No.5111gkd今天晚上我就要看到","FollowId":3950,"PlateId":5,"Status":0,"ReplyArr":"[]","UserId":174,"Time":1662701585,"MediaUrl":"[]","ReplyCount":0,"TopStatus":0,"LastReplyTime":1662701585,"SageAddId":"[]","SageSubId":"[]","Name":"k4zb5Iu"},{"Id":5115,"Title":"","Value":"No.5112我搜到了……","FollowId":3950,"PlateId":5,"Status":0,"ReplyArr":"[]","UserId":174,"Time":1662701806,"MediaUrl":"[{\"id\":\"F235904E-17B4-4CD5-8D58-A7F686EB135B\",\"url\":\"https://s2.loli.net/2022/09/09/N2a1W3GHJyemTXL.jpg\",\"thumbnailUrl\":\"https://s2.loli.net/2022/09/09/N2a1W3GHJyemTXL.jpg\"}]","ReplyCount":0,"TopStatus":0,"LastReplyTime":1662701806,"SageAddId":"[]","SageSubId":"[]","Name":"k4zb5Iu"}]