[{"Id":2831,"Title":"","Value":"No.2827\n不不不，白色皮糯米馅的是烧卖，黄色皮肉馅的是干蒸","FollowId":457,"PlateId":5,"Status":0,"ReplyArr":"[]","UserId":174,"Time":1654413722,"MediaUrl":"[]","ReplyCount":0,"TopStatus":0,"LastReplyTime":1654413722,"SageAddId":"[]","SageSubId":"[]","Name":"k4zb5Iu"},{"Id":2832,"Title":"","Value":"No.2828\n(　ﾟдﾟ)))赶紧去牙医诊所看看吧！","FollowId":457,"PlateId":5,"Status":0,"ReplyArr":"[]","UserId":174,"Time":1654413782,"MediaUrl":"[]","ReplyCount":0,"TopStatus":0,"LastReplyTime":1654413782,"SageAddId":"[]","SageSubId":"[]","Name":"k4zb5Iu"},{"Id":2833,"Title":"","Value":"梦见\n操场，短裤，长裤，集合\n经营店铺，旋转木马，马卡龙颜色，数码相机照片\n室友们，毕业，一个个单独吃饭\n爸爸妈妈，单车，小巷，凉茶铺，甜品店，糖水","FollowId":457,"PlateId":5,"Status":0,"ReplyArr":"[]","UserId":174,"Time":1654414055,"MediaUrl":"[]","ReplyCount":0,"TopStatus":0,"LastReplyTime":1654414055,"SageAddId":"[]","SageSubId":"[]","Name":"k4zb5Iu"},{"Id":2834,"Title":"","Value":"最近经常在网上看到一些咸甜大战\n想起高中的时候，学校旁边有一家新早餐店，应该是北方人开的，卖包子什么的，我还看到有豆腐花，远远的好像看到有浇棕色的酱汁，我猜是红糖吧？\n走近一看居然是酱油，上面还撒了葱花和辣椒圈？？？走了走了\n到傍晚放学的时候，早上有多少碗酱油豆花现在就还剩多少碗，后来第二天他们就改放白砂糖的了･ﾟ( ﾉヮ´ )","FollowId":457,"PlateId":5,"Status":0,"ReplyArr":"[]","UserId":174,"Time":1654415577,"MediaUrl":"[]","ReplyCount":0,"TopStatus":0,"LastReplyTime":1654415577,"SageAddId":"[]","SageSubId":"[]","Name":"k4zb5Iu"}]