[{"Id":2770,"Title":"","Value":"･ﾟ( ﾉヮ´ )连普通肠粉店都要等位","FollowId":457,"PlateId":5,"Status":0,"ReplyArr":"[]","UserId":174,"Time":1654254585,"MediaUrl":"[]","ReplyCount":0,"TopStatus":0,"LastReplyTime":1654254585,"SageAddId":"[]","SageSubId":"[]","Name":"k4zb5Iu"},{"Id":2771,"Title":"","Value":"连小学生都比我时尚( ・_ゝ・)","FollowId":457,"PlateId":5,"Status":0,"ReplyArr":"[]","UserId":174,"Time":1654254642,"MediaUrl":"[]","ReplyCount":0,"TopStatus":0,"LastReplyTime":1654254642,"SageAddId":"[]","SageSubId":"[]","Name":"k4zb5Iu"},{"Id":2772,"Title":"","Value":"喝个奶茶吧，我是1845，前面是1712……","FollowId":457,"PlateId":5,"Status":0,"ReplyArr":"[]","UserId":174,"Time":1654254889,"MediaUrl":"[]","ReplyCount":0,"TopStatus":0,"LastReplyTime":1654254889,"SageAddId":"[]","SageSubId":"[]","Name":"k4zb5Iu"},{"Id":2773,"Title":"","Value":"好多时尚潮人，土狗感到尴尬……","FollowId":457,"PlateId":5,"Status":0,"ReplyArr":"[]","UserId":174,"Time":1654254955,"MediaUrl":"[]","ReplyCount":0,"TopStatus":0,"LastReplyTime":1654254955,"SageAddId":"[]","SageSubId":"[]","Name":"k4zb5Iu"},{"Id":2774,"Title":"","Value":"复","FollowId":48,"PlateId":1,"Status":0,"ReplyArr":"[]","UserId":667,"Time":1654255062,"MediaUrl":"[]","ReplyCount":0,"TopStatus":0,"LastReplyTime":1654255062,"SageAddId":"[]","SageSubId":"[]","Name":"UBkgQGK"}]