[{"Id":2748,"Title":"","Value":"昨晚十二点醒了之后就睡不着，结果现在开始迷糊了","FollowId":457,"PlateId":5,"Status":0,"ReplyArr":"[]","UserId":174,"Time":1654225261,"MediaUrl":"[]","ReplyCount":0,"TopStatus":0,"LastReplyTime":1654225261,"SageAddId":"[]","SageSubId":"[]","Name":"k4zb5Iu"},{"Id":2749,"Title":"","Value":"(ヘ ﾟ∀。)ヘ阿巴阿巴阿巴","FollowId":457,"PlateId":5,"Status":0,"ReplyArr":"[]","UserId":174,"Time":1654225532,"MediaUrl":"[]","ReplyCount":0,"TopStatus":0,"LastReplyTime":1654225532,"SageAddId":"[]","SageSubId":"[]","Name":"k4zb5Iu"}]