[{"Id":2048,"Title":"","Value":"No.2045现在是521了，还是要和我跳舞(`ε´ )","FollowId":1186,"PlateId":1,"Status":0,"ReplyArr":"[]","UserId":382,"Time":1653092164,"MediaUrl":"[]","ReplyCount":0,"TopStatus":0,"LastReplyTime":1653092164,"SageAddId":"[]","SageSubId":"[]","Name":"YwyAAeU"},{"Id":2049,"Title":"","Value":"罐头鱼ﾟ早上好 ∀ﾟ)ノ","FollowId":1186,"PlateId":1,"Status":0,"ReplyArr":"[]","UserId":10,"Time":1653093708,"MediaUrl":"[]","ReplyCount":0,"TopStatus":0,"LastReplyTime":1653093708,"SageAddId":"[]","SageSubId":"[]","Name":"R5RCGeZ"}]