[{"Id":5116,"Title":"","Value":"No.4996\n数字花园的官方解释大概是:\n\n介于个人博客和wiki之间，是一个不断发展的笔记，没有严格的组织，本质上是探索性的，就像一个大花园，随便逛，没有固定的路线，而运营这个花园的人被称为园丁。","FollowId":4539,"PlateId":5,"Status":0,"ReplyArr":"[]","UserId":885,"Time":1662722255,"MediaUrl":"[]","ReplyCount":0,"TopStatus":0,"LastReplyTime":1662722255,"SageAddId":"[]","SageSubId":"[]","Name":"qNN2Byp"},{"Id":5117,"Title":"","Value":"开学了，时间变的越来越紧了。。。不过我还是会时不时来这里发帖的，我并没有遗忘这个串。","FollowId":4539,"PlateId":5,"Status":0,"ReplyArr":"[]","UserId":885,"Time":1662722316,"MediaUrl":"[]","ReplyCount":0,"TopStatus":0,"LastReplyTime":1662722316,"SageAddId":"[]","SageSubId":"[]","Name":"qNN2Byp"},{"Id":5118,"Title":"","Value":"看了很多开源图标库，在想自己是不是也可以搞一个。","FollowId":4539,"PlateId":5,"Status":0,"ReplyArr":"[]","UserId":885,"Time":1662722378,"MediaUrl":"[]","ReplyCount":0,"TopStatus":0,"LastReplyTime":1662722378,"SageAddId":"[]","SageSubId":"[]","Name":"qNN2Byp"},{"Id":5119,"Title":"","Value":"最近基本都是一点左右睡的，然后五点起床，幸好自己从不犯困，至多蔫蔫的。","FollowId":4539,"PlateId":5,"Status":0,"ReplyArr":"[]","UserId":885,"Time":1662722447,"MediaUrl":"[]","ReplyCount":0,"TopStatus":0,"LastReplyTime":1662722447,"SageAddId":"[]","SageSubId":"[]","Name":"qNN2Byp"},{"Id":5120,"Title":"","Value":"打算找个时间研究一下岛民岛的源代码，之前去github搜索过匿名版相关内容，只看到了4chan的油猴脚本、主题。。。还有一个似乎我看不太懂的冷门项目，终于出现了一个比较典型的开源匿名版项目了，激动的心，颤抖的手。","FollowId":4539,"PlateId":5,"Status":0,"ReplyArr":"[]","UserId":885,"Time":1662722864,"MediaUrl":"[]","ReplyCount":0,"TopStatus":0,"LastReplyTime":1662722864,"SageAddId":"[]","SageSubId":"[]","Name":"qNN2Byp"}]