[{"Id":4485,"Title":"","Value":"No.4483好累","FollowId":3950,"PlateId":5,"Status":0,"ReplyArr":"[]","UserId":10,"Time":1659573869,"MediaUrl":"[]","ReplyCount":0,"TopStatus":0,"LastReplyTime":1659573869,"SageAddId":"[]","SageSubId":"[]","Name":"R5RCGeZ"},{"Id":4486,"Title":"","Value":"No.4484直播是要面对百样人的啦( ´_っ`)","FollowId":457,"PlateId":5,"Status":0,"ReplyArr":"[]","UserId":10,"Time":1659573984,"MediaUrl":"[]","ReplyCount":0,"TopStatus":0,"LastReplyTime":1659573984,"SageAddId":"[]","SageSubId":"[]","Name":"R5RCGeZ"},{"Id":4487,"Title":"","Value":"【哼哼哼，啊啊啊啊啊啊啊啊啊啊啊】","FollowId":4013,"PlateId":1,"Status":0,"ReplyArr":"[]","UserId":10,"Time":1659574010,"MediaUrl":"[]","ReplyCount":0,"TopStatus":0,"LastReplyTime":1659574010,"SageAddId":"[]","SageSubId":"[]","Name":"R5RCGeZ"}]