[{"Id":5966,"Title":"","Value":"No.5963(;´Д`)呜呜呜好累啊——","FollowId":5450,"PlateId":5,"Status":0,"ReplyArr":"[]","UserId":174,"Time":1667140497,"MediaUrl":"[]","ReplyCount":0,"TopStatus":0,"LastReplyTime":1667140497,"SageAddId":"[]","SageSubId":"[]","Name":"k4zb5Iu"},{"Id":5967,"Title":"","Value":"No.5964你是指0600还是1800\nNo.5965交完按金没有钱钱了，我去做姜汁牛奶好了( ﾟ∀。)","FollowId":5450,"PlateId":5,"Status":0,"ReplyArr":"[]","UserId":174,"Time":1667140571,"MediaUrl":"[]","ReplyCount":0,"TopStatus":0,"LastReplyTime":1667140571,"SageAddId":"[]","SageSubId":"[]","Name":"k4zb5Iu"}]