[{"Id":11886,"Title":"","Value":"在这里你可以钓鱼，然后被鱼钓走","FollowId":11875,"PlateId":1,"Status":0,"ReplyArr":"[]","UserId":19,"Time":1695922402,"MediaUrl":"[]","ReplyCount":0,"TopStatus":0,"LastReplyTime":1695922402,"SageAddId":"[]","SageSubId":"[]","Name":"edHaFax"},{"Id":11887,"Title":"","Value":"我反对( `д´)水果月饼好吃！","FollowId":11883,"PlateId":1,"Status":0,"ReplyArr":"[]","UserId":174,"Time":1695922413,"MediaUrl":"[]","ReplyCount":0,"TopStatus":0,"LastReplyTime":1695922413,"SageAddId":"[]","SageSubId":"[]","Name":"k4zb5Iu"},{"Id":11888,"Title":"","Value":"No.11885啥？蓝屏了( ﾟ∀。)？","FollowId":7627,"PlateId":5,"Status":0,"ReplyArr":"[]","UserId":174,"Time":1695922443,"MediaUrl":"[]","ReplyCount":0,"TopStatus":0,"LastReplyTime":1695922443,"SageAddId":"[]","SageSubId":"[]","Name":"k4zb5Iu"},{"Id":11889,"Title":"","Value":"那你用美图秀秀或者小红书p啊( ﾟ∀。)","FollowId":7627,"PlateId":5,"Status":0,"ReplyArr":"[]","UserId":174,"Time":1695922463,"MediaUrl":"[]","ReplyCount":0,"TopStatus":0,"LastReplyTime":1695922463,"SageAddId":"[]","SageSubId":"[]","Name":"k4zb5Iu"},{"Id":11890,"Title":"","Value":"想要买点早餐三明治吃，可是这里压根就不卖我想要的那种( ・_ゝ・)这个时候又会暗暗地想自己为什么不是便利的大城市本地人，从出生就输了呢\n啊，饭桌上比我小的也比我过得好很多呢，只有我是最最失败的，不懂怎么去和别人相处，也不知道想要什么，究竟是谁毁了我的人生……？\n其实也不是这一件小事就引出来这么多的，而是很多很多的日常小事，导致我无时不刻都在想这些事情，想自己四十岁以后该怎么办，这个工作也不算很顺利，说到底都是看运气罢了","FollowId":9937,"PlateId":5,"Status":0,"ReplyArr":"[]","UserId":1426,"Time":1695923776,"MediaUrl":"[]","ReplyCount":0,"TopStatus":0,"LastReplyTime":1695923776,"SageAddId":"[]","SageSubId":"[]","Name":"xWECqtX"}]