[{"Id":8811,"Title":"","Value":"No.8692草，是我误会r5r了( ﾟ∀。)7原来是你( `д´)σ","FollowId":8679,"PlateId":1,"Status":0,"ReplyArr":"[]","UserId":174,"Time":1680942893,"MediaUrl":"[]","ReplyCount":0,"TopStatus":0,"LastReplyTime":1680942893,"SageAddId":"[]","SageSubId":"[]","Name":"k4zb5Iu"},{"Id":8812,"Title":"","Value":"No.8809虱子多了不痒的r5r( ´д`)","FollowId":8788,"PlateId":2,"Status":0,"ReplyArr":"[]","UserId":174,"Time":1680943055,"MediaUrl":"[]","ReplyCount":0,"TopStatus":0,"LastReplyTime":1680943055,"SageAddId":"[]","SageSubId":"[]","Name":"k4zb5Iu"},{"Id":8813,"Title":"","Value":"No.8810鲶鱼娘因为catfish( ﾟ∀。)\n念渝——念念不忘，至死不渝\n廿屿——有种双岛记的感觉\n姩妤——都是美女的意思( ﾟ∀。)","FollowId":8804,"PlateId":1,"Status":0,"ReplyArr":"[]","UserId":174,"Time":1680943431,"MediaUrl":"[]","ReplyCount":0,"TopStatus":0,"LastReplyTime":1680943431,"SageAddId":"[]","SageSubId":"[]","Name":"k4zb5Iu"}]