[{"Id":7833,"Title":"","Value":"我怀疑她还在睡觉然后狠狠迟到(`ᝫ´ )","FollowId":7627,"PlateId":5,"Status":0,"ReplyArr":"[]","UserId":174,"Time":1676794251,"MediaUrl":"[]","ReplyCount":0,"TopStatus":0,"LastReplyTime":1676794251,"SageAddId":"[]","SageSubId":"[]","Name":"k4zb5Iu"},{"Id":7834,"Title":"","Value":"某日BBS版面\n\n【置顶帖】BBS显示用户房号，请各位友善发言，遵守住户守则，营造良好网络环境.\n——0521：我能问一问这个公寓的房号到底是怎么定的吗？？？就我这5层，0538、0520、0505，这都什么？那些房号被吃了吗？\n——0505：楼上冷静点，习惯就好，话说你房号不错，521。\n——0520：日常刷帖。回复0521：emmm这都什么我其实也不好说了……不过说是被吃掉了还挺贴切的，是知道些什么没。\n——0521：？\n被吃了？\n【置顶帖】心理健康测试\n——0144：这题出的……梦回高考。\n——0202：同感↑\n——0202：话说难道只有我对这些题测试心理健康的效果有疑问吗？\n——0144：知识就是力，知识就是力，知识就是力。\n【热帖】有没有去过异常管理局的铁子\n【热帖】对匿名版/q/求助串的深入分析，速进\n【热帖】818这个公寓的前世今生（还有两三个重复的帖子）\n【精选】0444十年来回复合集","FollowId":7102,"PlateId":1,"Status":0,"ReplyArr":"[]","UserId":1052,"Time":1676794363,"MediaUrl":"[]","ReplyCount":0,"TopStatus":0,"LastReplyTime":1676794363,"SageAddId":"[]","SageSubId":"[]","Name":"dwyLdXp"}]