[{"Id":11239,"Title":"","Value":"No.11235上面那辆颜色好酷，低保和黄色确实很复古了","FollowId":7627,"PlateId":5,"Status":0,"ReplyArr":"[]","UserId":174,"Time":1692179739,"MediaUrl":"[]","ReplyCount":0,"TopStatus":0,"LastReplyTime":1692179739,"SageAddId":"[]","SageSubId":"[]","Name":"k4zb5Iu"},{"Id":11240,"Title":"","Value":"现在出发去喝酒(`ᝫ´ )","FollowId":7627,"PlateId":5,"Status":0,"ReplyArr":"[]","UserId":174,"Time":1692179761,"MediaUrl":"[]","ReplyCount":0,"TopStatus":0,"LastReplyTime":1692179761,"SageAddId":"[]","SageSubId":"[]","Name":"k4zb5Iu"}]