[{"Id":11616,"Title":"","Value":"No.11611\n还是区块链，都快die了|∀` )","FollowId":7627,"PlateId":5,"Status":0,"ReplyArr":"[]","UserId":10,"Time":1694656040,"MediaUrl":"[]","ReplyCount":0,"TopStatus":0,"LastReplyTime":1694656040,"SageAddId":"[]","SageSubId":"[]","Name":"R5RCGeZ"},{"Id":11617,"Title":"","Value":"No.11613\n买一送一，挺好|∀` )","FollowId":7627,"PlateId":5,"Status":0,"ReplyArr":"[]","UserId":10,"Time":1694656127,"MediaUrl":"[]","ReplyCount":0,"TopStatus":0,"LastReplyTime":1694656127,"SageAddId":"[]","SageSubId":"[]","Name":"R5RCGeZ"},{"Id":11618,"Title":"","Value":"公司下载东西好快，现在在公司电脑搞了个yuzu模拟器，搞了个石头门0来玩一玩|∀` )","FollowId":7627,"PlateId":5,"Status":0,"ReplyArr":"[]","UserId":10,"Time":1694656189,"MediaUrl":"[]","ReplyCount":0,"TopStatus":0,"LastReplyTime":1694656189,"SageAddId":"[]","SageSubId":"[]","Name":"R5RCGeZ"}]