[{"Id":11511,"Title":"","Value":"突然发现已删除的串也能被引用出来！！！！！( ᑭ`д´)ᓀ))д´)ᑫ肉吃我一拳！！！！为什么岛民岛功能会这样不稳定呢","FollowId":7627,"PlateId":5,"Status":0,"ReplyArr":"[]","UserId":174,"Time":1694178070,"MediaUrl":"[]","ReplyCount":0,"TopStatus":0,"LastReplyTime":1694178070,"SageAddId":"[]","SageSubId":"[]","Name":"k4zb5Iu"},{"Id":11512,"Title":"","Value":"看了下以前的内容，岛app研发的串基本都没了\nhttps://aweidao1.com/t/37777146?r=43605542\u0026page=864","FollowId":7627,"PlateId":5,"Status":0,"ReplyArr":"[]","UserId":174,"Time":1694180586,"MediaUrl":"[{\"id\":\"075a03a17b1efb862624e9ac1cf87a4b.png\",\"url\":\"https://islander-image.juhuan.store/075a03a17b1efb862624e9ac1cf87a4b.png\",\"thumbnailUrl\":\"https://islander-image.juhuan.store/075a03a17b1efb862624e9ac1cf87a4b.png\"}]","ReplyCount":0,"TopStatus":0,"LastReplyTime":1694180586,"SageAddId":"[]","SageSubId":"[]","Name":"k4zb5Iu"},{"Id":11513,"Title":"","Value":"No.11511其实是不是因为我只是删了主串，但是回复串没有发出来呢","FollowId":7627,"PlateId":5,"Status":0,"ReplyArr":"[]","UserId":174,"Time":1694180658,"MediaUrl":"[]","ReplyCount":0,"TopStatus":0,"LastReplyTime":1694180658,"SageAddId":"[]","SageSubId":"[]","Name":"k4zb5Iu"}]