[{"Id":11326,"Title":"","Value":"澡\n大暴雨真来了，超级暴雨，幸好是上班前两小时下完了","FollowId":7627,"PlateId":5,"Status":0,"ReplyArr":"[]","UserId":174,"Time":1692947101,"MediaUrl":"[{\"id\":\"e076bd5de884dbe2a98c0718a225989e.jpg\",\"url\":\"https://islander-image.juhuan.store/e076bd5de884dbe2a98c0718a225989e.jpg\",\"thumbnailUrl\":\"https://islander-image.juhuan.store/e076bd5de884dbe2a98c0718a225989e.jpg\"}]","ReplyCount":0,"TopStatus":0,"LastReplyTime":1692947101,"SageAddId":"[]","SageSubId":"[]","Name":"k4zb5Iu"}]