[{"Id":8548,"Title":"","Value":"No.8547哪样的世界？","FollowId":7627,"PlateId":5,"Status":0,"ReplyArr":"[]","UserId":174,"Time":1679908363,"MediaUrl":"[]","ReplyCount":0,"TopStatus":0,"LastReplyTime":1679908363,"SageAddId":"[]","SageSubId":"[]","Name":"k4zb5Iu"},{"Id":8549,"Title":"","Value":"而且我觉得里面单独的把ioi列为头号针对公司总觉得就是缺了点什么，就是整个剧本下来稍微有种幼稚感，英雄打坏蛋那种传统单一线路","FollowId":7627,"PlateId":5,"Status":0,"ReplyArr":"[]","UserId":174,"Time":1679908451,"MediaUrl":"[]","ReplyCount":0,"TopStatus":0,"LastReplyTime":1679908451,"SageAddId":"[]","SageSubId":"[]","Name":"k4zb5Iu"},{"Id":8550,"Title":"","Value":"(╬ﾟдﾟ)","FollowId":7627,"PlateId":5,"Status":0,"ReplyArr":"[]","UserId":174,"Time":1679910026,"MediaUrl":"[{\"id\":\"4ed1479070da79145a3a460faced4444.jpg\",\"url\":\"https://islander-image.juhuan.store/4ed1479070da79145a3a460faced4444.jpg\",\"thumbnailUrl\":\"https://islander-image.juhuan.store/4ed1479070da79145a3a460faced4444.jpg\"}]","ReplyCount":0,"TopStatus":0,"LastReplyTime":1679910026,"SageAddId":"[]","SageSubId":"[]","Name":"k4zb5Iu"}]