[{"Id":9644,"Title":"","Value":"No.9643最烦谜语人了( ᑭ`д´)ᓀ))д´)ᑫ","FollowId":7627,"PlateId":5,"Status":0,"ReplyArr":"[]","UserId":174,"Time":1684228275,"MediaUrl":"[]","ReplyCount":0,"TopStatus":0,"LastReplyTime":1684228275,"SageAddId":"[]","SageSubId":"[]","Name":"k4zb5Iu"},{"Id":9645,"Title":"","Value":"520朋友叫我去她那里玩，肯定是想让我当电灯泡！！","FollowId":7627,"PlateId":5,"Status":0,"ReplyArr":"[]","UserId":174,"Time":1684229135,"MediaUrl":"[]","ReplyCount":0,"TopStatus":0,"LastReplyTime":1684229135,"SageAddId":"[]","SageSubId":"[]","Name":"k4zb5Iu"}]